shindan_cli/__init__.py
shindan_cli/constants.py
shindan_cli/get_results.py
shindan_cli/interactive.py
shindan_cli/main.py
shindan_cli/models.py
shindan_cli/py.typed
shindan_cli/shindan.py
shindan_cli-2.2.0.dist-info/METADATA
shindan_cli-2.2.0.dist-info/WHEEL
shindan_cli-2.2.0.dist-info/entry_points.txt
shindan_cli-2.2.0.dist-info/licenses/LICENSE
shindan_cli-2.2.0.dist-info/RECORD
