Metadata-Version: 2.4
Name: shindan-cli
Version: 2.2.0
Summary: ShindanMaker (https://shindanmaker.com) CLI
Project-URL: Repository, https://github.com/eggplants/shindan-cli
Author-email: eggplants <w10776e8w@yahoo.co.jp>
License: MIT
License-File: LICENSE
Keywords: cli,shindanmaker
Classifier: Development Status :: 3 - Alpha
Classifier: License :: OSI Approved :: MIT License
Classifier: Programming Language :: Python :: 3 :: Only
Classifier: Programming Language :: Python :: 3.10
Classifier: Programming Language :: Python :: 3.11
Classifier: Programming Language :: Python :: 3.12
Classifier: Programming Language :: Python :: 3.13
Classifier: Programming Language :: Python :: 3.14
Classifier: Typing :: Typed
Requires-Python: <4,>=3.10
Requires-Dist: beautifulsoup4<5,>=4.12.3
Requires-Dist: cloudscraper<2,>=1.2.71
Requires-Dist: lxml<7,>=5.3
Requires-Dist: requests<3,>=2.32.3
